groove-dl
setup.cfg
setup.py
Groove_dl.egg-info/PKG-INFO
Groove_dl.egg-info/SOURCES.txt
Groove_dl.egg-info/dependency_links.txt
Groove_dl.egg-info/top_level.txt
groove/__init__.py
groove/connector.py
groove/downloader.py