Metadata-Version: 1.0
Name: Groove-dl
Version: 0.1
Summary: Grooveshark song downloader
Home-page: https://github.com/PierreRambaud/groove-dl
Author: Pierre Rambaud (GoT)
Author-email: UNKNOWN
License: GPLv3
Platform: UNKNOWN
